pagekey_sitegen/__init__.py
pagekey_sitegen/__main__.py
pagekey_sitegen/cli.py
pagekey_sitegen/generator.py
pagekey_sitegen/templates/next/.eslintrc.json
pagekey_sitegen/templates/next/next.config.js
pagekey_sitegen/templates/next/package.json
pagekey_sitegen/templates/next/postcss.config.js
pagekey_sitegen/templates/next/src/lib/Layout.tsx
pagekey_sitegen/templates/next/src/pages/_app.tsx
pagekey_sitegen/templates/next/src/pages/_document.tsx
pagekey_sitegen/templates/next/src/styles/globals.css
pagekey_sitegen/templates/next/tailwind.config.ts
pagekey_sitegen/templates/next/tsconfig.json
pagekey_sitegen/templates/sphinx/Makefile
pagekey_sitegen/templates/sphinx/conf.py
pagekey_sitegen/templates/sphinx/make.bat
pagekey_sitegen-3.1.0.dist-info/METADATA
pagekey_sitegen-3.1.0.dist-info/WHEEL
pagekey_sitegen-3.1.0.dist-info/entry_points.txt
pagekey_sitegen-3.1.0.dist-info/RECORD
